mlx/jira_traceability/__init__.py
mlx/jira_traceability/_version.py
mlx/jira_traceability/jira_interaction.py
mlx/jira_traceability/jira_traceability.py
mlx/jira_traceability/jira_utils.py
mlx_jira_traceability-2.2.2.dist-info/licenses/LICENSE
tests/test_jira_interaction.py
mlx_jira_traceability-2.2.2.dist-info/METADATA
mlx_jira_traceability-2.2.2.dist-info/WHEEL
mlx_jira_traceability-2.2.2.dist-info/top_level.txt
mlx_jira_traceability-2.2.2.dist-info/RECORD
