Metadata-Version: 2.4
Name: mlx.jira-traceability
Version: 2.2.2
Summary: Sphinx plugin to create Jira tickets based on traceable items
Author-email: Jasper Craeghs <jce@melexis.com>
License-Expression: Apache-2.0
Project-URL: Homepage, https://github.com/melexis/jira-traceability
Project-URL: Repository, https://github.com/melexis/jira-traceability
Project-URL: Issues, https://github.com/melexis/jira-traceability/issues
Keywords: traceability,jira,sphinx
Classifier: Development Status :: 4 - Beta
Classifier: Framework :: Sphinx :: Extension
Classifier: Intended Audience :: Developers
Classifier: Operating System :: OS Independent
Classifier: Programming Language :: Python
Classifier: Programming Language :: Python :: 3.10
Classifier: Programming Language :: Python :: 3.11
Classifier: Programming Language :: Python :: 3.12
Classifier: Programming Language :: Python :: 3.13
Classifier: Topic :: Documentation :: Sphinx
Classifier: Topic :: Software Development :: Bug Tracking
Classifier: Topic :: Utilities
Requires-Python: >=3.10
License-File: LICENSE
Requires-Dist: Sphinx>=2.1
Requires-Dist: jira>=3.10.5
Requires-Dist: mlx.traceability>=11.0.0
Dynamic: license-file
